hf_clean_benchmarks/__init__.py
hf_clean_benchmarks/_modidx.py
hf_clean_benchmarks/cli.py
hf_clean_benchmarks/core.py
hf_clean_benchmarks-0.0.1.dist-info/LICENSE
hf_clean_benchmarks-0.0.1.dist-info/METADATA
hf_clean_benchmarks-0.0.1.dist-info/WHEEL
hf_clean_benchmarks-0.0.1.dist-info/entry_points.txt
hf_clean_benchmarks-0.0.1.dist-info/top_level.txt
hf_clean_benchmarks-0.0.1.dist-info/RECORD
