Metadata-Version: 2.1
Name: hf-clean-benchmarks
Version: 0.0.1
Summary: This repository contains code for cleaning your training data of benchmark data to help combat data snooping.
Home-page: https://github.com/ncoop57/hf_clean_benchmarks
Author: ncoop57
Author-email: nacooper01@wm.edu
License: Apache Software License 2.0
Keywords: nbdev jupyter notebook python
Classifier: Development Status :: 4 - Beta
Classifier: Intended Audience :: Developers
Classifier: Natural Language :: English
Classifier: Programming Language :: Python :: 3.7
Classifier: Programming Language :: Python :: 3.8
Classifier: Programming Language :: Python :: 3.9
Classifier: Programming Language :: Python :: 3.10
Classifier: License :: OSI Approved :: Apache Software License
Requires-Python: >=3.7
License-File: LICENSE
Requires-Dist: datasets
Requires-Dist: datasketch
Requires-Dist: fastcore
Requires-Dist: rich
Provides-Extra: dev
